yeah/__init__.py
yeah/yeah.py
yeah-0.0.1.dist-info/LICENSE
yeah-0.0.1.dist-info/METADATA
yeah-0.0.1.dist-info/WHEEL
yeah-0.0.1.dist-info/top_level.txt
yeah-0.0.1.dist-info/RECORD
