Metadata-Version: 2.1
Name: yeah
Version: 0.0.1
Summary: yeah!
Home-page: https://github.com/MuchenSun/yeah
Author: Muchen Sun
License: UNKNOWN
Platform: UNKNOWN
Requires-Python: >=3.6
Requires-Dist: jax
